{
  "op3d_schema": "printer",
  "op3d_schema_version": "0.1.0",
  "id": "Qidi/X-Plus-Pro",
  "maintainer": {
    "name": "OpenPrint3D Community",
    "maintainer_type": "community",
    "website": "https://github.com/OpenPrint3D/OpenPrint3D"
  },
  "manufacturer": "Qidi",
  "model": "X-Plus Pro",
  "variant": "Stock",
  "build_volume": { "x": 300, "y": 300, "z": 340, "shape": "rectangular", "origin": "front_left" },
  "kinematics": "corexy",
  "axes": {
    "x": { "max_speed": 600, "max_accel": 30000 },
    "y": { "max_speed": 600, "max_accel": 30000 },
    "z": { "max_speed": 20, "max_accel": 500 }
  },
  "extruders": [{
    "id": "tool0",
    "nozzle_diameter": 0.4,
    "nozzle_material": "hardened-steel",
    "max_temp": 370,
    "min_temp": 170,
    "retraction_supported": true
  }],
  "bed": { "heated": true, "max_temp": 130, "surface_type": "PEI-textured" },
  "chamber": { "heated": true, "max_temp": 65, "passive": false },
  "firmware": { "flavor": "klipper", "identifier": "Qidi X-Plus Pro Firmware" },
  "network": { "has_wifi": true, "has_ethernet": true, "supports_lan_api": true },
  "links": {
    "product_page": "https://www.qidipro.com/x-plus-pro"
  },
  "tags": ["premium", "corexy", "direct-drive", "large-build", "enclosed", "high-speed", "klipper", "heated-chamber", "370c-capable"],
  "notes": "Qidi X-Plus Pro. Professional CoreXY with Klipper firmware, active chamber heating to 65°C, 370°C hotend for PEEK and high-temp materials, and 600mm/s max speed.",
  "x_cura": {
    "definition": "qidi_xpluspro",
    "definition_changes": {
      "machine_width": 300,
      "machine_depth": 300,
      "machine_height": 340,
      "nozzle_size": 0.4,
      "heated_bed": true,
      "machine_heated_bed": true,
      "bed_temperature": 60,
      "nozzle_temperature": 200
    }
  },
  "x_prusaslicer": {
    "printer_model": "X-Plus Pro",
    "vendor": "Qidi",
    "filament_diameter": 1.75,
    "nozzle_diameter": 0.4,
    "bed_shape": "rectangular",
    "bed_size": "300x300",
    "print_height": 340,
    "printer_technology": "FFF"
  },
  "x_orca": {
    "machine_name": "X-Plus Pro",
    "machine_manufacturer": "Qidi",
    "bed_x": 300,
    "bed_y": 300,
    "height": 340,
    "nozzle_diameter": 0.4,
    "filament_diameter": 1.75,
    "kinematics": "corexy"
  },
  "x_bambu": {
    "product_id": "qidi_xpluspro",
    "series": "X-Plus",
    "support_lidar": false,
    "support_ams": false,
    "support_ams_lite": false,
    "max_speed": 600,
    "active_chamber_heating": true,
    "max_temp": 370
  }
}
